<?xml version="1.0" encoding="UTF-8" standalone="yes"?>
<tns:time xmlns:tns="http://www.thiagosoares.com.br/time">
    <registroGeral>1</registroGeral>
    <nome>Santos</nome>
    <estadio>
        <nome>Vila Belmiro</nome>
        <capacidade>14000</capacidade>
    </estadio>
    <jogadores>
        <jogador matricula="1">
            <nome>Thiago Soares</nome>
            <dataNascimento>1991-07-17</dataNascimento>
            <posicao>ATAQUE</posicao>
            <lesionado>false</lesionado>
        </jogador>
        <jogador matricula="2">
            <nome>Wagner Souza</nome>
            <dataNascimento>1990-05-07</dataNascimento>
            <posicao>GOLEIRO</posicao>
            <lesionado>false</lesionado>
        </jogador>
        <jogador matricula="3">
            <nome>Luiz Carlos</nome>
            <dataNascimento>1989-09-01</dataNascimento>
            <posicao>MEIO_CAMPO</posicao>
            <lesionado>false</lesionado>
        </jogador>
        <jogador matricula="4">
            <nome>Pedro Henrique</nome>
            <dataNascimento>1989-10-13</dataNascimento>
            <posicao>ZAGUEIRO</posicao>
            <lesionado>true</lesionado>
        </jogador>
        <jogador matricula="5">
            <nome>Jackson Silva</nome>
            <dataNascimento>1970-01-27</dataNascimento>
            <posicao>MEIO_CAMPO</posicao>
            <lesionado>false</lesionado>
        </jogador>
    </jogadores>
    <valorMonetario>55000000</valorMonetario>
</tns:time>
